{
  "settings": {
    "migrated": 6,
    "iconPacksPath": ".obsidian/icons",
    "fontSize": 16,
    "emojiStyle": "native",
    "iconColor": null,
    "recentlyUsedIcons": [
      "LiVault",
      "LiTestTubeDiagonal",
      "LiFolderKanban",
      "LiFolderEdit",
      "LiMap"
    ],
    "recentlyUsedIconsSize": 5,
    "rules": [],
    "extraMargin": {
      "top": 0,
      "right": 4,
      "bottom": 0,
      "left": 0
    },
    "iconInTabsEnabled": false,
    "iconInTitleEnabled": false,
    "iconInTitlePosition": "above",
    "iconInFrontmatterEnabled": false,
    "iconInFrontmatterFieldName": "icon",
    "iconColorInFrontmatterFieldName": "iconColor",
    "iconsBackgroundCheckEnabled": false,
    "iconsInNotesEnabled": true,
    "iconsInLinksEnabled": true,
    "iconIdentifier": ":",
    "lucideIconPackType": "native",
    "debugMode": false,
    "useInternalPlugins": false
  },
  "content": "LiFolderEdit",
  "quartz": "LiFolderCode",
  "LICENSE.md": "LiScale",
  "README.md": "LiBookMarked",
  "content/BLOG": "LiPenTool",
  "content/BRAINSTORMING": "LiBrain",
  "content/CAV": "LiClapperboard",
  "content/img": "LiImages",
  "content/DREAMCLOUDS": "LiCloudSun",
  "content/COURS": "LiAlbum",
  "content/TUTO": "LiVideotape",
  "content/RESSOURCES": "LiFolderArchive",
  "content/ODOE": "LiRainbow",
  "content/soon.md": "LiBadge",
  "content/index.md": "LiMap",
  "content/PS": "LiTestTubeDiagonal",
  "content/VAATIGAMES": "LiVault"
}